mif/__init__.py
mif/__main__.py
mif/grammar.bnf
mif-0.5.dist-info/licenses/LICENSE
mif-0.5.dist-info/METADATA
mif-0.5.dist-info/WHEEL
mif-0.5.dist-info/top_level.txt
mif-0.5.dist-info/RECORD
