Metadata-Version: 2.4
Name: mif
Version: 0.5
Summary: reading and writing MIF files
Home-page: https://github.com/agrif/mif/
Author: Aaron Griffith
Author-email: aargri@gmail.com
License: MIT
Project-URL: Source, https://github.com/agrif/mif/
Project-URL: Documentation, https://mif.readthedocs.io/en/latest/
Keywords: memory mif quartus
Platform: any
Classifier: Development Status :: 4 - Beta
Classifier: Intended Audience :: Developers
Classifier: Topic :: Software Development :: Libraries :: Python Modules
Classifier: Topic :: Scientific/Engineering :: Electronic Design Automation (EDA)
Classifier: License :: OSI Approved :: MIT License
Classifier: Programming Language :: Python :: 3
Requires-Python: >=3.5
License-File: LICENSE
Requires-Dist: numpy>=1.17.0
Requires-Dist: lark-parser>=0.8.0
Requires-Dist: importlib-resources<6.0,>=5.12
Provides-Extra: docs
Requires-Dist: mkdocs<1.3,>=1.2; extra == "docs"
Requires-Dist: mkautodoc>=0.2.0; extra == "docs"
Dynamic: author
Dynamic: author-email
Dynamic: classifier
Dynamic: description
Dynamic: description-content-type
Dynamic: home-page
Dynamic: keywords
Dynamic: license
Dynamic: license-file
Dynamic: platform
Dynamic: project-url
Dynamic: provides-extra
Dynamic: requires-dist
Dynamic: requires-python
Dynamic: summary
